{"elements":[{"id":"JRnuLBShigUx1pg-r3mXa","type":"freedraw","x":360.8000183105469,"y":233.51251983642578,"width":0.0001,"height":0.0001,"angle":0,"strokeColor":"#000","backgroundColor":"transparent","fillStyle":"hachure","strokeWidth":1,"strokeStyle":"solid","roughness":1,"opacity":100,"groupIds":[],"strokeSharpness":"round","seed":1691897078,"version":3,"versionNonce":829374006,"isDeleted":false,"boundElements":null,"updated":1664785834852,"link":null,"points":[[0,0],[0.0001,0.0001]],"pressures":[],"simulatePressure":true,"lastCommittedPoint":[0.0001,0.0001]},{"id":"uuYuTaAEi2ZQ4uTYhWdVm","type":"freedraw","x":399.20001220703125,"y":204.7125015258789,"width":0.800018310546875,"height":3.20001220703125,"angle":0,"strokeColor":"#000","backgroundColor":"transparent","fillStyle":"hachure","strokeWidth":1,"strokeStyle":"solid","roughness":1,"opacity":100,"groupIds":[],"strokeSharpness":"round","seed":1322477610,"version":6,"versionNonce":1191649782,"isDeleted":false,"boundElements":null,"updated":1664785836677,"link":null,"points":[[0,0],[0,1.600006103515625],[-0.800018310546875,3.20001220703125],[0,0]],"pressures":[],"simulatePressure":true,"lastCommittedPoint":[-0.800018310546875,3.20001220703125]}],"appState":{"theme":"dark","collaborators":[],"currentChartType":"bar","currentItemBackgroundColor":"transparent","currentItemEndArrowhead":"arrow","currentItemFillStyle":"hachure","currentItemFontFamily":1,"currentItemFontSize":20,"currentItemLinearStrokeSharpness":"round","currentItemOpacity":100,"currentItemRoughness":1,"currentItemStartArrowhead":null,"currentItemStrokeColor":"#000","currentItemStrokeSharpness":"sharp","currentItemStrokeStyle":"solid","currentItemStrokeWidth":1,"currentItemTextAlign":"left","cursorButton":"down","draggingElement":null,"editingElement":null,"editingGroupId":null,"editingLinearElement":null,"elementLocked":false,"elementType":"freedraw","penMode":false,"penDetected":false,"errorMessage":null,"exportBackground":true,"exportScale":1,"exportEmbedScene":false,"exportWithDarkMode":false,"fileHandle":null,"gridSize":null,"isBindingEnabled":true,"isLibraryOpen":false,"isLoading":false,"isResizing":false,"isRotating":false,"lastPointerDownWith":"touch","multiElement":null,"name":"Obsidian Math Plus Drawing","openMenu":null,"openPopup":null,"pasteDialog":{"shown":false,"data":null},"previousSelectedElementIds":{},"resizingElement":null,"scrolledOutside":true,"scrollX":0,"scrollY":0,"selectedElementIds":{"uuYuTaAEi2ZQ4uTYhWdVm":false},"selectedGroupIds":{},"selectionElement":null,"shouldCacheIgnoreZoom":false,"showHelpDialog":false,"showStats":false,"startBoundElement":null,"suggestedBindings":[],"toastMessage":null,"viewBackgroundColor":"#fff0","zenModeEnabled":false,"zoom":{"value":1},"viewModeEnabled":false,"pendingImageElement":null,"showHyperlinkPopup":false,"offsetLeft":0,"offsetTop":0,"width":0,"height":0},"scrollToContent":false,"libraryItems":[]}